{"config": {"view": {"continuousWidth": 400, "continuousHeight": 300, "strokeWidth": 0}, "title": {"dx": 60, "dy": -15, "fontSize": 15}}, "data": {"name": "data-36e43b9870d4661cc89b1cef73b9a8ae"}, "mark": "bar", "encoding": {"color": {"field": "cat", "legend": {"labelFontSize": 12, "symbolSize": 400}, "scale": {"domain": ["No", "S\u00ed"], "reverse": true, "scheme": "spectral"}, "title": null, "type": "nominal"}, "column": {"field": "seg2", "header": {"labelFontSize": 15}, "sort": {"field": "order"}, "title": null, "type": "nominal"}, "order": {"field": "order", "sort": "descending", "type": "quantitative"}, "row": {"field": "seg1", "header": {"labelFontSize": 15}, "sort": {"field": "order"}, "title": null, "type": "nominal"}, "tooltip": [{"field": "cat", "title": "Valor", "type": "nominal"}, {"field": "prop", "format": ".1%", "title": "Estimaci\u00f3n", "type": "quantitative"}, {"field": "lower", "format": ".1%", "title": "L\u00edmite inferior", "type": "quantitative"}, {"field": "upper", "format": ".1%", "title": "L\u00edmite superior", "type": "quantitative"}], "x": {"axis": {"labelAngle": 0, "labelFontSize": 11}, "field": "Medici\u00f3n", "sort": {"field": "order"}, "title": null, "type": "nominal"}, "y": {"axis": {"format": "%", "labelFontSize": 11}, "field": "prop", "scale": {"nice": false}, "title": null, "type": "quantitative"}}, "height": 175, "resolve": {"axis": {"x": "independent", "y": "independent"}}, "selection": {"selector445": {"type": "multi", "fields": ["cat"], "bind": "legend", "on": "click", "toggle": "true"}, "selector446": {"type": "interval", "bind": "scales", "encodings": ["x", "y"]}}, "title": ["Poblaci\u00f3n con familiares no convivientes con COVID-19 en cada medici\u00f3n seg\u00fan sexo y edad (porcentajes e intervalos de confianza al 95%)"], "transform": [{"filter": {"selection": "selector445"}}], "width": 175, "$schema": "https://vega.github.io/schema/vega-lite/v4.17.0.json", "datasets": {"data-36e43b9870d4661cc89b1cef73b9a8ae": [{"Medici\u00f3n": "M1", "seg1": "Hombre", "seg2": "16-24", "cat": "No", "prop": 0.9200227339412789, "lower": 0.875686540179542, "upper": 0.9553501811328982, "order": 0}, {"Medici\u00f3n": "M1", "seg1": "Hombre", "seg2": "16-24", "cat": "S\u00ed", "prop": 0.07997726605872119, "lower": 0.0446498188671016, "upper": 0.12431345982045787, "order": 1}, {"Medici\u00f3n": "M1", "seg1": "Hombre", "seg2": "25-34", "cat": "No", "prop": 0.9669756264756254, "lower": 0.9293648275148516, "upper": 0.9857779664479518, "order": 2}, {"Medici\u00f3n": "M1", "seg1": "Hombre", "seg2": "25-34", "cat": "S\u00ed", "prop": 0.03302437352437449, "lower": 0.014222033552048633, "upper": 0.07063517248514908, "order": 3}, {"Medici\u00f3n": "M1", "seg1": "Hombre", "seg2": "35-44", "cat": "No", "prop": 0.9477787540366862, "lower": 0.9172438552386536, "upper": 0.9699317603238522, "order": 4}, {"Medici\u00f3n": "M1", "seg1": "Hombre", "seg2": "35-44", "cat": "S\u00ed", "prop": 0.05222124596331376, "lower": 0.030068239676147916, "upper": 0.08275614476134643, "order": 5}, {"Medici\u00f3n": "M1", "seg1": "Hombre", "seg2": "45-54", "cat": "No", "prop": 0.905198854772907, "lower": 0.8624343370328, "upper": 0.9338934238987673, "order": 6}, {"Medici\u00f3n": "M1", "seg1": "Hombre", "seg2": "45-54", "cat": "S\u00ed", "prop": 0.09480114522709325, "lower": 0.06610657610123268, "upper": 0.13756566296719996, "order": 7}, {"Medici\u00f3n": "M1", "seg1": "Hombre", "seg2": "55-64", "cat": "No", "prop": 0.948126444431852, "lower": 0.9157685755643932, "upper": 0.9728969273021912, "order": 8}, {"Medici\u00f3n": "M1", "seg1": "Hombre", "seg2": "55-64", "cat": "S\u00ed", "prop": 0.05187355556814795, "lower": 0.027103072697808955, "upper": 0.08423142443560767, "order": 9}, {"Medici\u00f3n": "M1", "seg1": "Hombre", "seg2": "65 Y MAS", "cat": "No", "prop": 0.9380685117394124, "lower": 0.9001329573212372, "upper": 0.9655914383896006, "order": 10}, {"Medici\u00f3n": "M1", "seg1": "Hombre", "seg2": "65 Y MAS", "cat": "S\u00ed", "prop": 0.06193148826058749, "lower": 0.034408561610399374, "upper": 0.09986704267876229, "order": 11}, {"Medici\u00f3n": "M1", "seg1": "Hombre", "seg2": "Total", "cat": "No", "prop": 0.9374174370844433, "lower": 0.922665537495378, "upper": 0.9486660556575485, "order": 12}, {"Medici\u00f3n": "M1", "seg1": "Hombre", "seg2": "Total", "cat": "S\u00ed", "prop": 0.06258256291555675, "lower": 0.051333944342451775, "upper": 0.07733446250462209, "order": 13}, {"Medici\u00f3n": "M1", "seg1": "Mujer", "seg2": "16-24", "cat": "No", "prop": 0.9328989097307183, "lower": 0.8790177638410219, "upper": 0.9631771314560345, "order": 14}, {"Medici\u00f3n": "M1", "seg1": "Mujer", "seg2": "16-24", "cat": "S\u00ed", "prop": 0.06710109026928174, "lower": 0.03682286854396567, "upper": 0.12098223615897867, "order": 15}, {"Medici\u00f3n": "M1", "seg1": "Mujer", "seg2": "25-34", "cat": "No", "prop": 0.9496829440724861, "lower": 0.9116512753828322, "upper": 0.9739389824823338, "order": 16}, {"Medici\u00f3n": "M1", "seg1": "Mujer", "seg2": "25-34", "cat": "S\u00ed", "prop": 0.05031705592751393, "lower": 0.026061017517666214, "upper": 0.08834872461716768, "order": 17}, {"Medici\u00f3n": "M1", "seg1": "Mujer", "seg2": "35-44", "cat": "No", "prop": 0.8931515755171463, "lower": 0.8536696692219312, "upper": 0.9258093823911434, "order": 18}, {"Medici\u00f3n": "M1", "seg1": "Mujer", "seg2": "35-44", "cat": "S\u00ed", "prop": 0.10684842448285378, "lower": 0.0741906176088565, "upper": 0.14633033077806906, "order": 19}, {"Medici\u00f3n": "M1", "seg1": "Mujer", "seg2": "45-54", "cat": "No", "prop": 0.9208296340424083, "lower": 0.8884008746070975, "upper": 0.94460919990227, "order": 20}, {"Medici\u00f3n": "M1", "seg1": "Mujer", "seg2": "45-54", "cat": "S\u00ed", "prop": 0.07917036595759157, "lower": 0.05539080009772992, "upper": 0.11159912539290266, "order": 21}, {"Medici\u00f3n": "M1", "seg1": "Mujer", "seg2": "55-64", "cat": "No", "prop": 0.9239942867254233, "lower": 0.8851048933248153, "upper": 0.9515792712651417, "order": 22}, {"Medici\u00f3n": "M1", "seg1": "Mujer", "seg2": "55-64", "cat": "S\u00ed", "prop": 0.0760057132745769, "lower": 0.048420728734858115, "upper": 0.11489510667518445, "order": 23}, {"Medici\u00f3n": "M1", "seg1": "Mujer", "seg2": "65 Y MAS", "cat": "No", "prop": 0.9522673591692078, "lower": 0.9227549322566605, "upper": 0.9719032280329667, "order": 24}, {"Medici\u00f3n": "M1", "seg1": "Mujer", "seg2": "65 Y MAS", "cat": "S\u00ed", "prop": 0.04773264083079209, "lower": 0.028096771967033245, "upper": 0.07724506774333943, "order": 25}, {"Medici\u00f3n": "M1", "seg1": "Mujer", "seg2": "Total", "cat": "No", "prop": 0.9280023679630636, "lower": 0.9132420448072207, "upper": 0.9402306820514093, "order": 26}, {"Medici\u00f3n": "M1", "seg1": "Mujer", "seg2": "Total", "cat": "S\u00ed", "prop": 0.07199763203693653, "lower": 0.059769317948590764, "upper": 0.08675795519277946, "order": 27}, {"Medici\u00f3n": "M1", "seg1": "Total", "seg2": "16-24", "cat": "No", "prop": 0.926130274787015, "lower": 0.8926111126891327, "upper": 0.9504878954297874, "order": 28}, {"Medici\u00f3n": "M1", "seg1": "Total", "seg2": "16-24", "cat": "S\u00ed", "prop": 0.07386972521298497, "lower": 0.04951210457021271, "upper": 0.10738888731086697, "order": 29}, {"Medici\u00f3n": "M1", "seg1": "Total", "seg2": "25-34", "cat": "No", "prop": 0.9586847598269002, "lower": 0.9342826098206954, "upper": 0.9747556009386482, "order": 30}, {"Medici\u00f3n": "M1", "seg1": "Total", "seg2": "25-34", "cat": "S\u00ed", "prop": 0.04131524017309982, "lower": 0.025244399061351754, "upper": 0.06571739017930472, "order": 31}, {"Medici\u00f3n": "M1", "seg1": "Total", "seg2": "35-44", "cat": "No", "prop": 0.9201010949864857, "lower": 0.8957108056579567, "upper": 0.938459881167652, "order": 32}, {"Medici\u00f3n": "M1", "seg1": "Total", "seg2": "35-44", "cat": "S\u00ed", "prop": 0.0798989050135144, "lower": 0.06154011883234791, "upper": 0.10428919434204245, "order": 33}, {"Medici\u00f3n": "M1", "seg1": "Total", "seg2": "45-54", "cat": "No", "prop": 0.9133918736989156, "lower": 0.8907482039504164, "upper": 0.9319211848785026, "order": 34}, {"Medici\u00f3n": "M1", "seg1": "Total", "seg2": "45-54", "cat": "S\u00ed", "prop": 0.0866081263010843, "lower": 0.06807881512149762, "upper": 0.1092517960495838, "order": 35}, {"Medici\u00f3n": "M1", "seg1": "Total", "seg2": "55-64", "cat": "No", "prop": 0.9361741060466725, "lower": 0.9124051144057375, "upper": 0.954653883431065, "order": 36}, {"Medici\u00f3n": "M1", "seg1": "Total", "seg2": "55-64", "cat": "S\u00ed", "prop": 0.06382589395332743, "lower": 0.045346116568934856, "upper": 0.08759488559426244, "order": 37}, {"Medici\u00f3n": "M1", "seg1": "Total", "seg2": "65 Y MAS", "cat": "No", "prop": 0.9461916333660986, "lower": 0.9245578397099877, "upper": 0.9641098704196606, "order": 38}, {"Medici\u00f3n": "M1", "seg1": "Total", "seg2": "65 Y MAS", "cat": "S\u00ed", "prop": 0.053808366633901566, "lower": 0.035890129580339346, "upper": 0.07544216029001234, "order": 39}, {"Medici\u00f3n": "M1", "seg1": "Total", "seg2": "Total", "cat": "No", "prop": 0.932601109355137, "lower": 0.9222615267953053, "upper": 0.9411952611435841, "order": 40}, {"Medici\u00f3n": "M1", "seg1": "Total", "seg2": "Total", "cat": "S\u00ed", "prop": 0.06739889064486297, "lower": 0.05880473885641588, "upper": 0.07773847320469464, "order": 41}, {"Medici\u00f3n": "M2", "seg1": "Hombre", "seg2": "16-24", "cat": "No", "prop": 0.9211780107191263, "lower": 0.8678830783903057, "upper": 0.9598250440344311, "order": 42}, {"Medici\u00f3n": "M2", "seg1": "Hombre", "seg2": "16-24", "cat": "S\u00ed", "prop": 0.07882198928087367, "lower": 0.04017495596556886, "upper": 0.13211692160969438, "order": 43}, {"Medici\u00f3n": "M2", "seg1": "Hombre", "seg2": "25-34", "cat": "No", "prop": 0.9732925067774428, "lower": 0.9384022639465942, "upper": 0.9903320416530692, "order": 44}, {"Medici\u00f3n": "M2", "seg1": "Hombre", "seg2": "25-34", "cat": "S\u00ed", "prop": 0.026707493222557187, "lower": 0.009667958346931, "upper": 0.06159773605340691, "order": 45}, {"Medici\u00f3n": "M2", "seg1": "Hombre", "seg2": "35-44", "cat": "No", "prop": 0.9540948839701233, "lower": 0.92078015781809, "upper": 0.9745526253165349, "order": 46}, {"Medici\u00f3n": "M2", "seg1": "Hombre", "seg2": "35-44", "cat": "S\u00ed", "prop": 0.04590511602987666, "lower": 0.025447374683465057, "upper": 0.07921984218190989, "order": 47}, {"Medici\u00f3n": "M2", "seg1": "Hombre", "seg2": "45-54", "cat": "No", "prop": 0.9495452530543463, "lower": 0.9190513639947281, "upper": 0.9725167188418757, "order": 48}, {"Medici\u00f3n": "M2", "seg1": "Hombre", "seg2": "45-54", "cat": "S\u00ed", "prop": 0.050454746945653633, "lower": 0.027483281158124054, "upper": 0.08094863600527161, "order": 49}, {"Medici\u00f3n": "M2", "seg1": "Hombre", "seg2": "55-64", "cat": "No", "prop": 0.9522545353615902, "lower": 0.9159256024405253, "upper": 0.9748369372182619, "order": 50}, {"Medici\u00f3n": "M2", "seg1": "Hombre", "seg2": "55-64", "cat": "S\u00ed", "prop": 0.04774546463840973, "lower": 0.025163062781738035, "upper": 0.08407439755947485, "order": 51}, {"Medici\u00f3n": "M2", "seg1": "Hombre", "seg2": "65 Y MAS", "cat": "No", "prop": 0.9348477707558926, "lower": 0.8203088823973853, "upper": 0.9717307710985733, "order": 52}, {"Medici\u00f3n": "M2", "seg1": "Hombre", "seg2": "65 Y MAS", "cat": "S\u00ed", "prop": 0.06515222924410745, "lower": 0.02826922890142663, "upper": 0.17969111760261253, "order": 53}, {"Medici\u00f3n": "M2", "seg1": "Hombre", "seg2": "Total", "cat": "No", "prop": 0.9482847634630386, "lower": 0.931221400753424, "upper": 0.9612107938697779, "order": 54}, {"Medici\u00f3n": "M2", "seg1": "Hombre", "seg2": "Total", "cat": "S\u00ed", "prop": 0.051715236536961445, "lower": 0.03878920613022201, "upper": 0.06877859924657585, "order": 55}, {"Medici\u00f3n": "M2", "seg1": "Mujer", "seg2": "16-24", "cat": "No", "prop": 0.9200284579301434, "lower": 0.8670606445856229, "upper": 0.9614215698554422, "order": 56}, {"Medici\u00f3n": "M2", "seg1": "Mujer", "seg2": "16-24", "cat": "S\u00ed", "prop": 0.07997154206985661, "lower": 0.03857843014455786, "upper": 0.1329393554143773, "order": 57}, {"Medici\u00f3n": "M2", "seg1": "Mujer", "seg2": "25-34", "cat": "No", "prop": 0.9819379281434918, "lower": 0.9529833615878242, "upper": 0.9949281857252565, "order": 58}, {"Medici\u00f3n": "M2", "seg1": "Mujer", "seg2": "25-34", "cat": "S\u00ed", "prop": 0.018062071856508297, "lower": 0.005071814274743258, "upper": 0.047016638412175966, "order": 59}, {"Medici\u00f3n": "M2", "seg1": "Mujer", "seg2": "35-44", "cat": "No", "prop": 0.891229731570499, "lower": 0.8477633305201009, "upper": 0.9247719711195614, "order": 60}, {"Medici\u00f3n": "M2", "seg1": "Mujer", "seg2": "35-44", "cat": "S\u00ed", "prop": 0.10877026842950106, "lower": 0.0752280288804386, "upper": 0.1522366694798991, "order": 61}, {"Medici\u00f3n": "M2", "seg1": "Mujer", "seg2": "45-54", "cat": "No", "prop": 0.9396138700014578, "lower": 0.909743079819519, "upper": 0.9633627791507332, "order": 62}, {"Medici\u00f3n": "M2", "seg1": "Mujer", "seg2": "45-54", "cat": "S\u00ed", "prop": 0.060386129998542086, "lower": 0.03663722084926681, "upper": 0.09025692018048126, "order": 63}, {"Medici\u00f3n": "M2", "seg1": "Mujer", "seg2": "55-64", "cat": "No", "prop": 0.937267789947643, "lower": 0.886784223801853, "upper": 0.9675194114276274, "order": 64}, {"Medici\u00f3n": "M2", "seg1": "Mujer", "seg2": "55-64", "cat": "S\u00ed", "prop": 0.06273221005235695, "lower": 0.03248058857237244, "upper": 0.11321577619814698, "order": 65}, {"Medici\u00f3n": "M2", "seg1": "Mujer", "seg2": "65 Y MAS", "cat": "No", "prop": 0.9677218819886448, "lower": 0.9394066046365621, "upper": 0.9862645634576215, "order": 66}, {"Medici\u00f3n": "M2", "seg1": "Mujer", "seg2": "65 Y MAS", "cat": "S\u00ed", "prop": 0.03227811801135516, "lower": 0.01373543654237874, "upper": 0.06059339536343797, "order": 67}, {"Medici\u00f3n": "M2", "seg1": "Mujer", "seg2": "Total", "cat": "No", "prop": 0.9388645580139681, "lower": 0.9242511544186891, "upper": 0.9505157474832187, "order": 68}, {"Medici\u00f3n": "M2", "seg1": "Mujer", "seg2": "Total", "cat": "S\u00ed", "prop": 0.061135441986031956, "lower": 0.049484252516781305, "upper": 0.07574884558131063, "order": 69}, {"Medici\u00f3n": "M2", "seg1": "Total", "seg2": "16-24", "cat": "No", "prop": 0.9206234474147665, "lower": 0.885793633191783, "upper": 0.9484553414149737, "order": 70}, {"Medici\u00f3n": "M2", "seg1": "Total", "seg2": "16-24", "cat": "S\u00ed", "prop": 0.07937655258523343, "lower": 0.0515446585850265, "upper": 0.11420636680821729, "order": 71}, {"Medici\u00f3n": "M2", "seg1": "Total", "seg2": "25-34", "cat": "No", "prop": 0.9774278455412841, "lower": 0.9574678906794445, "upper": 0.9895736452192262, "order": 72}, {"Medici\u00f3n": "M2", "seg1": "Total", "seg2": "25-34", "cat": "S\u00ed", "prop": 0.022572154458715705, "lower": 0.010426354780773986, "upper": 0.04253210932055556, "order": 73}, {"Medici\u00f3n": "M2", "seg1": "Total", "seg2": "35-44", "cat": "No", "prop": 0.9225154380646249, "lower": 0.896356009325933, "upper": 0.9432898207969141, "order": 74}, {"Medici\u00f3n": "M2", "seg1": "Total", "seg2": "35-44", "cat": "S\u00ed", "prop": 0.07748456193537512, "lower": 0.05671017920308584, "upper": 0.1036439906740669, "order": 75}, {"Medici\u00f3n": "M2", "seg1": "Total", "seg2": "45-54", "cat": "No", "prop": 0.9443885636650787, "lower": 0.9234521037737038, "upper": 0.9612508318120644, "order": 76}, {"Medici\u00f3n": "M2", "seg1": "Total", "seg2": "45-54", "cat": "S\u00ed", "prop": 0.05561143633492126, "lower": 0.03874916818793542, "upper": 0.07654789622629582, "order": 77}, {"Medici\u00f3n": "M2", "seg1": "Total", "seg2": "55-64", "cat": "No", "prop": 0.9446389550802785, "lower": 0.9134507873117232, "upper": 0.965354044403095, "order": 78}, {"Medici\u00f3n": "M2", "seg1": "Total", "seg2": "55-64", "cat": "S\u00ed", "prop": 0.055361044919721485, "lower": 0.03464595559690489, "upper": 0.08654921268827645, "order": 79}, {"Medici\u00f3n": "M2", "seg1": "Total", "seg2": "65 Y MAS", "cat": "No", "prop": 0.953499785428394, "lower": 0.9097636634253199, "upper": 0.9728897917634549, "order": 80}, {"Medici\u00f3n": "M2", "seg1": "Total", "seg2": "65 Y MAS", "cat": "S\u00ed", "prop": 0.04650021457160601, "lower": 0.027110208236545228, "upper": 0.0902363365746803, "order": 81}, {"Medici\u00f3n": "M2", "seg1": "Total", "seg2": "Total", "cat": "No", "prop": 0.9434658080919224, "lower": 0.9322413554960324, "upper": 0.9518737398794326, "order": 82}, {"Medici\u00f3n": "M2", "seg1": "Total", "seg2": "Total", "cat": "S\u00ed", "prop": 0.05653419190807749, "lower": 0.0481262601205674, "upper": 0.06775864450396762, "order": 83}, {"Medici\u00f3n": "M3", "seg1": "Hombre", "seg2": "16-24", "cat": "No", "prop": 0.7805457045504272, "lower": 0.7063520449508084, "upper": 0.8490469567651253, "order": 84}, {"Medici\u00f3n": "M3", "seg1": "Hombre", "seg2": "16-24", "cat": "S\u00ed", "prop": 0.21945429544957284, "lower": 0.15095304323487463, "upper": 0.29364795504919167, "order": 85}, {"Medici\u00f3n": "M3", "seg1": "Hombre", "seg2": "25-34", "cat": "No", "prop": 0.8334047040555588, "lower": 0.7742170968587199, "upper": 0.8842554711919314, "order": 86}, {"Medici\u00f3n": "M3", "seg1": "Hombre", "seg2": "25-34", "cat": "S\u00ed", "prop": 0.16659529594444103, "lower": 0.11574452880806874, "upper": 0.22578290314128005, "order": 87}, {"Medici\u00f3n": "M3", "seg1": "Hombre", "seg2": "35-44", "cat": "No", "prop": 0.8323516799681714, "lower": 0.7864016724936655, "upper": 0.8720906430424544, "order": 88}, {"Medici\u00f3n": "M3", "seg1": "Hombre", "seg2": "35-44", "cat": "S\u00ed", "prop": 0.16764832003182867, "lower": 0.12790935695754574, "upper": 0.2135983275063344, "order": 89}, {"Medici\u00f3n": "M3", "seg1": "Hombre", "seg2": "45-54", "cat": "No", "prop": 0.8000347797575922, "lower": 0.7442874755765136, "upper": 0.8437399815372698, "order": 90}, {"Medici\u00f3n": "M3", "seg1": "Hombre", "seg2": "45-54", "cat": "S\u00ed", "prop": 0.19996522024240782, "lower": 0.1562600184627302, "upper": 0.2557125244234866, "order": 91}, {"Medici\u00f3n": "M3", "seg1": "Hombre", "seg2": "55-64", "cat": "No", "prop": 0.7934605942485681, "lower": 0.7419085793562146, "upper": 0.8406146466395659, "order": 92}, {"Medici\u00f3n": "M3", "seg1": "Hombre", "seg2": "55-64", "cat": "S\u00ed", "prop": 0.20653940575143193, "lower": 0.1593853533604334, "upper": 0.25809142064378526, "order": 93}, {"Medici\u00f3n": "M3", "seg1": "Hombre", "seg2": "65 Y MAS", "cat": "No", "prop": 0.8747949504914933, "lower": 0.8054769097556138, "upper": 0.9195719824002805, "order": 94}, {"Medici\u00f3n": "M3", "seg1": "Hombre", "seg2": "65 Y MAS", "cat": "S\u00ed", "prop": 0.12520504950850686, "lower": 0.08042801759971979, "upper": 0.19452309024438644, "order": 95}, {"Medici\u00f3n": "M3", "seg1": "Hombre", "seg2": "Total", "cat": "No", "prop": 0.8195359304160221, "lower": 0.796603530243874, "upper": 0.8393804572592451, "order": 96}, {"Medici\u00f3n": "M3", "seg1": "Hombre", "seg2": "Total", "cat": "S\u00ed", "prop": 0.18046406958397787, "lower": 0.1606195427407549, "upper": 0.20339646975612588, "order": 97}, {"Medici\u00f3n": "M3", "seg1": "Mujer", "seg2": "16-24", "cat": "No", "prop": 0.8269019796889016, "lower": 0.7681869449061661, "upper": 0.8744760417439671, "order": 98}, {"Medici\u00f3n": "M3", "seg1": "Mujer", "seg2": "16-24", "cat": "S\u00ed", "prop": 0.1730980203110983, "lower": 0.12552395825603296, "upper": 0.23181305509383363, "order": 99}, {"Medici\u00f3n": "M3", "seg1": "Mujer", "seg2": "25-34", "cat": "No", "prop": 0.8056360969287603, "lower": 0.7467830638046377, "upper": 0.8515886374203671, "order": 100}, {"Medici\u00f3n": "M3", "seg1": "Mujer", "seg2": "25-34", "cat": "S\u00ed", "prop": 0.19436390307123963, "lower": 0.14841136257963292, "upper": 0.2532169361953637, "order": 101}, {"Medici\u00f3n": "M3", "seg1": "Mujer", "seg2": "35-44", "cat": "No", "prop": 0.7699782299126172, "lower": 0.7244529089664173, "upper": 0.810192851503883, "order": 102}, {"Medici\u00f3n": "M3", "seg1": "Mujer", "seg2": "35-44", "cat": "S\u00ed", "prop": 0.2300217700873827, "lower": 0.18980714849611693, "upper": 0.27554709103358266, "order": 103}, {"Medici\u00f3n": "M3", "seg1": "Mujer", "seg2": "45-54", "cat": "No", "prop": 0.8115455988055865, "lower": 0.7688250518209504, "upper": 0.8487938208479987, "order": 104}, {"Medici\u00f3n": "M3", "seg1": "Mujer", "seg2": "45-54", "cat": "S\u00ed", "prop": 0.18845440119441373, "lower": 0.15120617915200152, "upper": 0.2311749481790496, "order": 105}, {"Medici\u00f3n": "M3", "seg1": "Mujer", "seg2": "55-64", "cat": "No", "prop": 0.7897540065749721, "lower": 0.7368621100720064, "upper": 0.8394420356671523, "order": 106}, {"Medici\u00f3n": "M3", "seg1": "Mujer", "seg2": "55-64", "cat": "S\u00ed", "prop": 0.2102459934250279, "lower": 0.16055796433284772, "upper": 0.2631378899279936, "order": 107}, {"Medici\u00f3n": "M3", "seg1": "Mujer", "seg2": "65 Y MAS", "cat": "No", "prop": 0.8540549607054493, "lower": 0.8037020063865018, "upper": 0.8925344168451012, "order": 108}, {"Medici\u00f3n": "M3", "seg1": "Mujer", "seg2": "65 Y MAS", "cat": "S\u00ed", "prop": 0.14594503929455063, "lower": 0.10746558315489874, "upper": 0.19629799361349806, "order": 109}, {"Medici\u00f3n": "M3", "seg1": "Mujer", "seg2": "Total", "cat": "No", "prop": 0.8096788662252684, "lower": 0.7903494090185488, "upper": 0.8286337230941617, "order": 110}, {"Medici\u00f3n": "M3", "seg1": "Mujer", "seg2": "Total", "cat": "S\u00ed", "prop": 0.1903211337747316, "lower": 0.17136627690583833, "upper": 0.20965059098145117, "order": 111}, {"Medici\u00f3n": "M3", "seg1": "Total", "seg2": "16-24", "cat": "No", "prop": 0.8034938586415017, "lower": 0.7482051658976152, "upper": 0.8455514506837415, "order": 112}, {"Medici\u00f3n": "M3", "seg1": "Total", "seg2": "16-24", "cat": "S\u00ed", "prop": 0.1965061413584981, "lower": 0.1544485493162585, "upper": 0.2517948341023848, "order": 113}, {"Medici\u00f3n": "M3", "seg1": "Total", "seg2": "25-34", "cat": "No", "prop": 0.8202174529044314, "lower": 0.7795545943886805, "upper": 0.854463357526568, "order": 114}, {"Medici\u00f3n": "M3", "seg1": "Total", "seg2": "25-34", "cat": "S\u00ed", "prop": 0.17978254709556857, "lower": 0.14553664247343204, "upper": 0.22044540561131953, "order": 115}, {"Medici\u00f3n": "M3", "seg1": "Total", "seg2": "35-44", "cat": "No", "prop": 0.8004066748625249, "lower": 0.7704314299023441, "upper": 0.8341542217579498, "order": 116}, {"Medici\u00f3n": "M3", "seg1": "Total", "seg2": "35-44", "cat": "S\u00ed", "prop": 0.1995933251374751, "lower": 0.16584577824205013, "upper": 0.22956857009765583, "order": 117}, {"Medici\u00f3n": "M3", "seg1": "Total", "seg2": "45-54", "cat": "No", "prop": 0.8059108200331357, "lower": 0.7699105869826793, "upper": 0.8383881031371696, "order": 118}, {"Medici\u00f3n": "M3", "seg1": "Total", "seg2": "45-54", "cat": "S\u00ed", "prop": 0.19408917996686406, "lower": 0.1616118968628298, "upper": 0.23008941301732044, "order": 119}, {"Medici\u00f3n": "M3", "seg1": "Total", "seg2": "55-64", "cat": "No", "prop": 0.7916041166868868, "lower": 0.7562924548695031, "upper": 0.8252080036800782, "order": 120}, {"Medici\u00f3n": "M3", "seg1": "Total", "seg2": "55-64", "cat": "S\u00ed", "prop": 0.20839588331311323, "lower": 0.17479199631992184, "upper": 0.24370754513049686, "order": 121}, {"Medici\u00f3n": "M3", "seg1": "Total", "seg2": "65 Y MAS", "cat": "No", "prop": 0.8630255051806405, "lower": 0.8238509355991485, "upper": 0.8939621120374145, "order": 122}, {"Medici\u00f3n": "M3", "seg1": "Total", "seg2": "65 Y MAS", "cat": "S\u00ed", "prop": 0.13697449481935958, "lower": 0.1060378879625852, "upper": 0.17614906440085126, "order": 123}, {"Medici\u00f3n": "M3", "seg1": "Total", "seg2": "Total", "cat": "No", "prop": 0.8144934976705137, "lower": 0.7990770658104803, "upper": 0.8298500272436358, "order": 124}, {"Medici\u00f3n": "M3", "seg1": "Total", "seg2": "Total", "cat": "S\u00ed", "prop": 0.18550650232948623, "lower": 0.17014997275636426, "upper": 0.2009229341895197, "order": 125}, {"Medici\u00f3n": "M4", "seg1": "Hombre", "seg2": "16-24", "cat": "No", "prop": 0.7736335750648381, "lower": 0.6952972046862947, "upper": 0.8510720710092987, "order": 126}, {"Medici\u00f3n": "M4", "seg1": "Hombre", "seg2": "16-24", "cat": "S\u00ed", "prop": 0.22636642493516188, "lower": 0.1489279289907013, "upper": 0.30470279531370525, "order": 127}, {"Medici\u00f3n": "M4", "seg1": "Hombre", "seg2": "25-34", "cat": "No", "prop": 0.7195236840971089, "lower": 0.657543084559537, "upper": 0.7914318760567682, "order": 128}, {"Medici\u00f3n": "M4", "seg1": "Hombre", "seg2": "25-34", "cat": "S\u00ed", "prop": 0.2804763159028908, "lower": 0.20856812394323168, "upper": 0.34245691544046303, "order": 129}, {"Medici\u00f3n": "M4", "seg1": "Hombre", "seg2": "35-44", "cat": "No", "prop": 0.7429235889144452, "lower": 0.686662987836487, "upper": 0.7954312791119796, "order": 130}, {"Medici\u00f3n": "M4", "seg1": "Hombre", "seg2": "35-44", "cat": "S\u00ed", "prop": 0.2570764110855547, "lower": 0.20456872088802006, "upper": 0.3133370121635126, "order": 131}, {"Medici\u00f3n": "M4", "seg1": "Hombre", "seg2": "45-54", "cat": "No", "prop": 0.7144366995781912, "lower": 0.6611996502111688, "upper": 0.7654033250197968, "order": 132}, {"Medici\u00f3n": "M4", "seg1": "Hombre", "seg2": "45-54", "cat": "S\u00ed", "prop": 0.2855633004218089, "lower": 0.23459667498020337, "upper": 0.3388003497888311, "order": 133}, {"Medici\u00f3n": "M4", "seg1": "Hombre", "seg2": "55-64", "cat": "No", "prop": 0.6927496174069676, "lower": 0.6328329281686296, "upper": 0.7519799410917111, "order": 134}, {"Medici\u00f3n": "M4", "seg1": "Hombre", "seg2": "55-64", "cat": "S\u00ed", "prop": 0.3072503825930322, "lower": 0.248020058908289, "upper": 0.36716707183137043, "order": 135}, {"Medici\u00f3n": "M4", "seg1": "Hombre", "seg2": "65 Y MAS", "cat": "No", "prop": 0.7693707414174037, "lower": 0.7026633669385116, "upper": 0.8273127765622449, "order": 136}, {"Medici\u00f3n": "M4", "seg1": "Hombre", "seg2": "65 Y MAS", "cat": "S\u00ed", "prop": 0.2306292585825965, "lower": 0.17268722343775486, "upper": 0.29733663306148833, "order": 137}, {"Medici\u00f3n": "M4", "seg1": "Hombre", "seg2": "Total", "cat": "No", "prop": 0.7349205827906004, "lower": 0.7109516301733089, "upper": 0.7620380625738213, "order": 138}, {"Medici\u00f3n": "M4", "seg1": "Hombre", "seg2": "Total", "cat": "S\u00ed", "prop": 0.26507941720939965, "lower": 0.23796193742617844, "upper": 0.289048369826691, "order": 139}, {"Medici\u00f3n": "M4", "seg1": "Mujer", "seg2": "16-24", "cat": "No", "prop": 0.683438233265292, "lower": 0.5953169026175716, "upper": 0.7549904344975578, "order": 140}, {"Medici\u00f3n": "M4", "seg1": "Mujer", "seg2": "16-24", "cat": "S\u00ed", "prop": 0.316561766734708, "lower": 0.24500956550244218, "upper": 0.4046830973824282, "order": 141}, {"Medici\u00f3n": "M4", "seg1": "Mujer", "seg2": "25-34", "cat": "No", "prop": 0.6648427254942851, "lower": 0.6048298242242519, "upper": 0.726483846309504, "order": 142}, {"Medici\u00f3n": "M4", "seg1": "Mujer", "seg2": "25-34", "cat": "S\u00ed", "prop": 0.3351572745057149, "lower": 0.27351615369049576, "upper": 0.3951701757757481, "order": 143}, {"Medici\u00f3n": "M4", "seg1": "Mujer", "seg2": "35-44", "cat": "No", "prop": 0.6697878767028279, "lower": 0.6256457165175601, "upper": 0.7194207802766894, "order": 144}, {"Medici\u00f3n": "M4", "seg1": "Mujer", "seg2": "35-44", "cat": "S\u00ed", "prop": 0.3302121232971723, "lower": 0.2805792197233107, "upper": 0.37435428348243993, "order": 145}, {"Medici\u00f3n": "M4", "seg1": "Mujer", "seg2": "45-54", "cat": "No", "prop": 0.6882275927046284, "lower": 0.6391682158512604, "upper": 0.7348538739855447, "order": 146}, {"Medici\u00f3n": "M4", "seg1": "Mujer", "seg2": "45-54", "cat": "S\u00ed", "prop": 0.3117724072953716, "lower": 0.265146126014455, "upper": 0.3608317841487392, "order": 147}, {"Medici\u00f3n": "M4", "seg1": "Mujer", "seg2": "55-64", "cat": "No", "prop": 0.6649028240247071, "lower": 0.6030207640504209, "upper": 0.7161652578661261, "order": 148}, {"Medici\u00f3n": "M4", "seg1": "Mujer", "seg2": "55-64", "cat": "S\u00ed", "prop": 0.33509717597529287, "lower": 0.28383474213387383, "upper": 0.39697923594957907, "order": 149}, {"Medici\u00f3n": "M4", "seg1": "Mujer", "seg2": "65 Y MAS", "cat": "No", "prop": 0.7777723788440968, "lower": 0.7225243466035597, "upper": 0.8345464589997038, "order": 150}, {"Medici\u00f3n": "M4", "seg1": "Mujer", "seg2": "65 Y MAS", "cat": "S\u00ed", "prop": 0.22222762115590322, "lower": 0.16545354100029616, "upper": 0.27747565339644026, "order": 151}, {"Medici\u00f3n": "M4", "seg1": "Mujer", "seg2": "Total", "cat": "No", "prop": 0.6943504501122304, "lower": 0.6691858604235463, "upper": 0.7166512391391228, "order": 152}, {"Medici\u00f3n": "M4", "seg1": "Mujer", "seg2": "Total", "cat": "S\u00ed", "prop": 0.3056495498877696, "lower": 0.2833487608608774, "upper": 0.33081413957645367, "order": 153}, {"Medici\u00f3n": "M4", "seg1": "Total", "seg2": "16-24", "cat": "No", "prop": 0.7284551328650618, "lower": 0.6714997254928472, "upper": 0.7825695784554713, "order": 154}, {"Medici\u00f3n": "M4", "seg1": "Total", "seg2": "16-24", "cat": "S\u00ed", "prop": 0.27154486713493814, "lower": 0.2174304215445288, "upper": 0.3285002745071533, "order": 155}, {"Medici\u00f3n": "M4", "seg1": "Total", "seg2": "25-34", "cat": "No", "prop": 0.6939448285493702, "lower": 0.6474151242350729, "upper": 0.741114713395848, "order": 156}, {"Medici\u00f3n": "M4", "seg1": "Total", "seg2": "25-34", "cat": "S\u00ed", "prop": 0.30605517145062966, "lower": 0.25888528660415194, "upper": 0.35258487576492736, "order": 157}, {"Medici\u00f3n": "M4", "seg1": "Total", "seg2": "35-44", "cat": "No", "prop": 0.7054543750773069, "lower": 0.6674592588055263, "upper": 0.7400536018739026, "order": 158}, {"Medici\u00f3n": "M4", "seg1": "Total", "seg2": "35-44", "cat": "S\u00ed", "prop": 0.2945456249226931, "lower": 0.2599463981260977, "upper": 0.33254074119447397, "order": 159}, {"Medici\u00f3n": "M4", "seg1": "Total", "seg2": "45-54", "cat": "No", "prop": 0.7011561817561948, "lower": 0.6660063622495106, "upper": 0.7337666317755881, "order": 160}, {"Medici\u00f3n": "M4", "seg1": "Total", "seg2": "45-54", "cat": "S\u00ed", "prop": 0.2988438182438053, "lower": 0.26623336822441157, "upper": 0.33399363775048924, "order": 161}, {"Medici\u00f3n": "M4", "seg1": "Total", "seg2": "55-64", "cat": "No", "prop": 0.6785540767213586, "lower": 0.6384951628203801, "upper": 0.7204176368104096, "order": 162}, {"Medici\u00f3n": "M4", "seg1": "Total", "seg2": "55-64", "cat": "S\u00ed", "prop": 0.3214459232786415, "lower": 0.27958236318959073, "upper": 0.36150483717961995, "order": 163}, {"Medici\u00f3n": "M4", "seg1": "Total", "seg2": "65 Y MAS", "cat": "No", "prop": 0.7741291438550993, "lower": 0.7279057691760691, "upper": 0.8137143394095716, "order": 164}, {"Medici\u00f3n": "M4", "seg1": "Total", "seg2": "65 Y MAS", "cat": "S\u00ed", "prop": 0.22587085614490068, "lower": 0.1862856605904283, "upper": 0.27209423082393086, "order": 165}, {"Medici\u00f3n": "M4", "seg1": "Total", "seg2": "Total", "cat": "No", "prop": 0.7141667201224867, "lower": 0.6964203679111819, "upper": 0.730998199437541, "order": 166}, {"Medici\u00f3n": "M4", "seg1": "Total", "seg2": "Total", "cat": "S\u00ed", "prop": 0.2858332798775132, "lower": 0.26900180056245915, "upper": 0.3035796320888181, "order": 167}]}}